newshomepages/__init__.py
newshomepages/accessibility.py
newshomepages/adstxt.py
newshomepages/archive.py
newshomepages/batch.py
newshomepages/hyperlinks.py
newshomepages/mosaic.py
newshomepages/robotstxt.py
newshomepages/screenshot.py
newshomepages/slack.py
newshomepages/toot.py
newshomepages/utils.py
newshomepages/wayback.py
newshomepages/analyze/__init__.py
newshomepages/analyze/__main__.py
newshomepages/analyze/cli.py
newshomepages/analyze/drudge.py
newshomepages/analyze/lighthouse.py
newshomepages/analyze/us_right_wing.py
newshomepages/extensions/adguard/manifest.json
newshomepages/extensions/adguard/runtime.js
newshomepages/extensions/adguard/_locales/ar/messages.json
newshomepages/extensions/adguard/_locales/be/messages.json
newshomepages/extensions/adguard/_locales/bg/messages.json
newshomepages/extensions/adguard/_locales/bn/messages.json
newshomepages/extensions/adguard/_locales/ca/messages.json
newshomepages/extensions/adguard/_locales/cs/messages.json
newshomepages/extensions/adguard/_locales/da/messages.json
newshomepages/extensions/adguard/_locales/de/messages.json
newshomepages/extensions/adguard/_locales/el/messages.json
newshomepages/extensions/adguard/_locales/en/messages.json
newshomepages/extensions/adguard/_locales/es/messages.json
newshomepages/extensions/adguard/_locales/es_419/messages.json
newshomepages/extensions/adguard/_locales/et/messages.json
newshomepages/extensions/adguard/_locales/fa/messages.json
newshomepages/extensions/adguard/_locales/fi/messages.json
newshomepages/extensions/adguard/_locales/fil/messages.json
newshomepages/extensions/adguard/_locales/fr/messages.json
newshomepages/extensions/adguard/_locales/he/messages.json
newshomepages/extensions/adguard/_locales/hi/messages.json
newshomepages/extensions/adguard/_locales/hr/messages.json
newshomepages/extensions/adguard/_locales/hu/messages.json
newshomepages/extensions/adguard/_locales/hy/messages.json
newshomepages/extensions/adguard/_locales/id/messages.json
newshomepages-0.0.117.dist-info/licenses/LICENSE
newshomepages-0.0.117.dist-info/METADATA
newshomepages-0.0.117.dist-info/WHEEL
newshomepages-0.0.117.dist-info/entry_points.txt
newshomepages-0.0.117.dist-info/top_level.txt
newshomepages-0.0.117.dist-info/RECORD
