Metadata-Version: 2.4
Name: newshomepages
Version: 0.0.117
Summary: An open-source archive that gathers, saves, shares and analyzes news homepages
Home-page: https://homepages.news
Author: Ben Welsh
Author-email: b@palewi.re
License: GPLv3
Project-URL: Maintainer, https://palewi.re/who-is-ben-welsh/
Project-URL: Source, https://github.com/palewire/news-homepages
Project-URL: Tracker, https://github.com/palewire/news-homepages/issues
Classifier: Development Status :: 5 - Production/Stable
Classifier: Programming Language :: Python
Classifier: Programming Language :: Python :: 3
Classifier: Programming Language :: Python :: 3.10
Classifier: Programming Language :: Python :: 3.11
Classifier: License :: OSI Approved :: GNU General Public License v3 (GPLv3)
Classifier: Topic :: System :: Archiving
Classifier: Topic :: Internet :: WWW/HTTP :: Dynamic Content :: News/Diary
License-File: LICENSE
Requires-Dist: click
Requires-Dist: pytz
Requires-Dist: internetarchive>=5.0.4
Requires-Dist: python-slugify
Requires-Dist: playwright
Requires-Dist: jinja2
Requires-Dist: shot-scraper
Requires-Dist: pillow
Requires-Dist: pandas
Requires-Dist: rich
Requires-Dist: iso3166
Requires-Dist: python-iso639
Requires-Dist: certifi
Requires-Dist: requests
Requires-Dist: retry
Requires-Dist: storysniffer
Requires-Dist: spacy
Requires-Dist: spectra
Requires-Dist: sqlean
Requires-Dist: Mastodon.py
Requires-Dist: sqlite-robotstxt
Requires-Dist: libtorrent
Dynamic: author
Dynamic: author-email
Dynamic: classifier
Dynamic: description
Dynamic: description-content-type
Dynamic: home-page
Dynamic: license
Dynamic: license-file
Dynamic: project-url
Dynamic: requires-dist
Dynamic: summary
